{
  "project_info": {
    "project_number": "651397958438",
    "project_id": "cubic-run-sakakiki",
    "storage_bucket": "cubic-run-sakakiki.firebasestorage.app"
  },
  "client": [
    {
      "client_info": {
        "mobilesdk_app_id": "1:651397958438:android:f985418a622d8234da4fe7",
        "android_client_info": {
          "package_name": "com.sakakiki.com.unity.cubic.run"
        }
      },
      "oauth_client": [
        {
          "client_id": "651397958438-v7i8i23e7op0fs8un40spfrpht20ipgc.apps.googleusercontent.com",
          "client_type": 3
        }
      ],
      "api_key": [
        {
          "current_key": "AIzaSyA6InJ97WwRpmTv63p2zMEuRny0oc3kKC8"
        }
      ],
      "services": {
        "appinvite_service": {
          "other_platform_oauth_client": [
            {
              "client_id": "651397958438-v7i8i23e7op0fs8un40spfrpht20ipgc.apps.googleusercontent.com",
              "client_type": 3
            }
          ]
        }
      }
    }
  ],
  "configuration_version": "1"
}